fifo_design.v
// Synchronous FIFO with almost full/empty and count signals
module fifo_sync #(
    parameter DATA_WIDTH = 8,
    parameter FIFO_DEPTH = 8,
    parameter ADDR_WIDTH = $clog2(FIFO_DEPTH),
    parameter ALMOST_FULL_THRESHOLD = FIFO_DEPTH - 1,
    parameter ALMOST_EMPTY_THRESHOLD = 1
)(
    input  wire                   clk,
    input  wire                   rst_n,
    input  wire                   wr_en,
    input  wire                   rd_en,
    input  wire [DATA_WIDTH-1:0]  data_in,
    output reg  [DATA_WIDTH-1:0]  data_out,
    output wire                   full,
    output wire                   empty,
    output reg  [ADDR_WIDTH:0]    fifo_count,
    output wire                   almost_full,
    output wire                   almost_empty
);

    // Internal registers
    reg [DATA_WIDTH-1:0] mem [0:FIFO_DEPTH-1];
    reg [ADDR_WIDTH:0]   wr_ptr, rd_ptr;

    // Write pointer and data
    always @(posedge clk or negedge rst_n) begin
        if (!rst_n) begin
            wr_ptr <= 0;
        end else if (wr_en && !full) begin
            mem[wr_ptr[ADDR_WIDTH-1:0]] <= data_in;
            wr_ptr <= wr_ptr + 1;
        end
    end

    // Read pointer and data
    always @(posedge clk or negedge rst_n) begin
        if (!rst_n) begin
            rd_ptr <= 0;
            data_out <= 0;
        end else begin
            if (rd_en && !empty) begin
                data_out <= mem[rd_ptr[ADDR_WIDTH-1:0]];
                rd_ptr <= rd_ptr + 1;
            end else if (rd_en && empty) begin
                data_out <= 0; // Underflow protection
            end
            // Simultaneous read/write
            if (wr_en && rd_en && !full && !empty) begin
                data_out <= mem[rd_ptr[ADDR_WIDTH-1:0]];
                rd_ptr <= rd_ptr + 1;
            end
        end
    end

    // FIFO count logic
    always @(posedge clk or negedge rst_n) begin
        if (!rst_n) begin
            fifo_count <= 0;
        end else begin
            case ({wr_en && !full, rd_en && !empty})
                2'b10: fifo_count <= fifo_count + 1; // Write only
                2'b01: fifo_count <= fifo_count - 1; // Read only
                2'b11: fifo_count <= fifo_count;     // Simultaneous read/write
                default: fifo_count <= fifo_count;   // No operation or invalid
            endcase
        end
    end

    // Status flags
    assign empty = (fifo_count == 0);
    assign full = (fifo_count == FIFO_DEPTH);
    assign almost_empty = (fifo_count <= ALMOST_EMPTY_THRESHOLD);
    assign almost_full = (fifo_count >= ALMOST_FULL_THRESHOLD);

endmodule

testbench_fifo.v
`timescale 1ns / 1ns
module fifo_tb;

    // Parameters
    parameter DATA_WIDTH = 8;
    parameter FIFO_DEPTH = 8;
    parameter ADDR_WIDTH = $clog2(FIFO_DEPTH);
    parameter CLK_PERIOD = 10;

    // Signals
    reg                  clk = 0;
    reg                  rst_n = 0;
    reg                  wr_en = 0;
    reg                  rd_en = 0;
    reg [DATA_WIDTH-1:0] data_in;
    wire [DATA_WIDTH-1:0] data_out;
    wire                 full, empty, almost_full, almost_empty;
    wire [ADDR_WIDTH:0]  fifo_count;

    // DUT instantiation
    fifo_sync #(
        .DATA_WIDTH(DATA_WIDTH),
        .FIFO_DEPTH(FIFO_DEPTH)
    ) dut (
        .clk(clk), .rst_n(rst_n),
        .wr_en(wr_en), .rd_en(rd_en),
        .data_in(data_in), .data_out(data_out),
        .full(full), .empty(empty),
        .almost_full(almost_full), .almost_empty(almost_empty),
        .fifo_count(fifo_count)
    );

    // Clock generation
    always #(CLK_PERIOD/2) clk = ~clk;

    initial begin
        $dumpfile("fifo_tb.vcd");
        $dumpvars(0, fifo_tb);
        $display("===================================");
        $display("=== FIFO SIMULATION STARTED ===");
        $display("===================================");

        // Initialize signals
        rst_n = 0;
        wr_en = 0;
        rd_en = 0;
        data_in = 0;

        // Test Case 1: Reset FIFO
        $display("\n=== TEST CASE 1: RESET FIFO ===");
        #20 rst_n = 1;
        @(posedge clk);
        $display("Status at Time=%0t ns:", $time);
        $display("-----------------------------------");
        $display("rst_n=%b | wr_en=%b | rd_en=%b | data_in=%h | data_out=%h | fifo_count=%d",
                rst_n, wr_en, rd_en, data_in, data_out, fifo_count);
        $display("Flags: empty=%b | full=%b | almost_empty=%b | almost_full=%b",
                empty, full, almost_empty, almost_full);
        $display("Expected: *empty=1, full=0, almost_empty=1, almost_full=0, fifo_count=0*");
        $display("Actual:   empty=%b, full=%b, almost_empty=%b, almost_full=%b, fifo_count=%d",
                empty, full, almost_empty, almost_full, fifo_count);
        $display("-----------------------------------");

        // Test Case 2: Write until almost full
        $display("\n=== TEST CASE 2: WRITE UNTIL ALMOST FULL ===");
        repeat(FIFO_DEPTH-1) begin
            @(posedge clk);
            wr_en = 1;
            data_in = data_in + 1;
            $display("Time=%0t ns: WRITE - data_in=%h | fifo_count=%d",
                    $time, data_in, fifo_count);
        end
        @(posedge clk) wr_en = 0;
        $display("-----------------------------------");
        $display("Status at Time=%0t ns:", $time);
        $display("rst_n=%b | wr_en=%b | rd_en=%b | data_in=%h | data_out=%h | fifo_count=%d",
                rst_n, wr_en, rd_en, data_in, data_out, fifo_count);
        $display("Flags: empty=%b | full=%b | almost_empty=%b | almost_full=%b",
                empty, full, almost_empty, almost_full);
        $display("Expected: *empty=0, full=0, almost_empty=0, almost_full=1, fifo_count=7*");
        $display("Actual:   empty=%b, full=%b, almost_empty=%b, almost_full=%b, fifo_count=%d",
                empty, full, almost_empty, almost_full, fifo_count);
        $display("-----------------------------------");

        // Test Case 3: Write to full and attempt overflow
        $display("\n=== TEST CASE 3: WRITE TO FULL AND ATTEMPT OVERFLOW ===");
        @(posedge clk);
        wr_en = 1;
        data_in = data_in + 1;
        $display("Time=%0t ns: WRITE - data_in=%h | fifo_count=%d",
                $time, data_in, fifo_count);
        @(posedge clk);
        wr_en = 1; // Overflow attempt
        data_in = 8'hFF;
        $display("Time=%0t ns: *OVERFLOW ATTEMPT* - data_in=%h | fifo_count=%d",
                $time, data_in, fifo_count);
        @(posedge clk) wr_en = 0;
        $display("-----------------------------------");
        $display("Status at Time=%0t ns:", $time);
        $display("rst_n=%b | wr_en=%b | rd_en=%b | data_in=%h | data_out=%h | fifo_count=%d",
                rst_n, wr_en, rd_en, data_in, data_out, fifo_count);
        $display("Flags: empty=%b | full=%b | almost_empty=%b | almost_full=%b",
                empty, full, almost_empty, almost_full);
        $display("Expected: *empty=0, full=1, almost_empty=0, almost_full=1, fifo_count=8*");
        $display("Actual:   empty=%b, full=%b, almost_empty=%b, almost_full=%b, fifo_count=%d",
                empty, full, almost_empty, almost_full, fifo_count);
        $display("-----------------------------------");

        // Test Case 4: Read until almost empty
        $display("\n=== TEST CASE 4: READ UNTIL ALMOST EMPTY ===");
        repeat(FIFO_DEPTH-1) begin
            @(posedge clk);
            rd_en = 1;
            @(posedge clk);
            $display("Time=%0t ns: READ - data_out=%h | fifo_count=%d",
                    $time, data_out, fifo_count);
            rd_en = 0;
        end
        $display("-----------------------------------");
        $display("Status at Time=%0t ns:", $time);
        $display("rst_n=%b | wr_en=%b | rd_en=%b | data_in=%h | data_out=%h | fifo_count=%d",
                rst_n, wr_en, rd_en, data_in, data_out, fifo_count);
        $display("Flags: empty=%b | full=%b | almost_empty=%b | almost_full=%b",
                empty, full, almost_empty, almost_full);
        $display("Expected: *empty=0, full=0, almost_empty=1, almost_full=0, fifo_count=1*");
        $display("Actual:   empty=%b, full=%b, almost_empty=%b, almost_full=%b, fifo_count=%d",
                empty, full, almost_empty, almost_full, fifo_count);
        $display("-----------------------------------");

        // Test Case 5: Read to empty and attempt underflow
        $display("\n=== TEST CASE 5: READ TO EMPTY AND ATTEMPT UNDERFLOW ===");
        @(posedge clk);
        rd_en = 1;
        @(posedge clk);
        $display("Time=%0t ns: READ - data_out=%h | fifo_count=%d",
                $time, data_out, fifo_count);
        rd_en = 0;
        @(posedge clk);
        rd_en = 1; // Underflow attempt
        @(posedge clk);
        $display("Time=%0t ns: *UNDERFLOW ATTEMPT* - data_out=%h | fifo_count=%d",
                $time, data_out, fifo_count);
        @(posedge clk) rd_en = 0;
        $display("-----------------------------------");
        $display("Status at Time=%0t ns:", $time);
        $display("rst_n=%b | wr_en=%b | rd_en=%b | data_in=%h | data_out=%h | fifo_count=%d",
                rst_n, wr_en, rd_en, data_in, data_out, fifo_count);
        $display("Flags: empty=%b | full=%b | almost_empty=%b | almost_full=%b",
                empty, full, almost_empty, almost_full);
        $display("Expected: *empty=1, full=0, almost_empty=1, almost_full=0, fifo_count=0*");
        $display("Actual:   empty=%b, full=%b, almost_empty=%b, almost_full=%b, fifo_count=%d",
                empty, full, almost_empty, almost_full, fifo_count);
        $display("-----------------------------------");

        // Test Case 6: Simultaneous read and write
        $display("\n=== TEST CASE 6: SIMULTANEOUS READ AND WRITE ===");
        // Write one element first
        @(posedge clk);
        wr_en = 1;
        data_in = 8'h10;
        $display("Time=%0t ns: WRITE - data_in=%h | fifo_count=%d",
                $time, data_in, fifo_count);
        @(posedge clk) wr_en = 0;
        repeat(3) begin
            @(posedge clk);
            wr_en = 1;
            rd_en = 1;
            data_in = data_in + 1;
            @(posedge clk);
            $display("Time=%0t ns: SIM R/W - data_in=%h | data_out=%h | fifo_count=%d",
                    $time, data_in, data_out, fifo_count);
            wr_en = 0;
            rd_en = 0;
        end
        $display("-----------------------------------");
        $display("Status at Time=%0t ns:", $time);
        $display("rst_n=%b | wr_en=%b | rd_en=%b | data_in=%h | data_out=%h | fifo_count=%d",
                rst_n, wr_en, rd_en, data_in, data_out, fifo_count);
        $display("Flags: empty=%b | full=%b | almost_empty=%b | almost_full=%b",
                empty, full, almost_empty, almost_full);
        $display("Expected: *fifo_count remains stable during simultaneous read/write*");
        $display("Actual:   fifo_count=%d", fifo_count);
        $display("-----------------------------------");

        // End simulation
        #20 $display("===================================");
        $display("=== SIMULATION COMPLETE ===");
        $display("===================================");
        $finish;
    end

    // Monitor for debugging 
    initial begin
        $monitor("Time=%0t ns | rst_n=%b | wr_en=%b | rd_en=%b | data_in=%h | data_out=%h | fifo_count=%d",
                 $time, rst_n, wr_en, rd_en, data_in, data_out, fifo_count);
    end

endmodule

fifo_tb.vcd
$date
	Sat Jul 26 21:06:50 2025
$end
$version
	Icarus Verilog
$end
$timescale
	1ns
$end
$scope module fifo_tb $end
$var wire 1 ! full $end
$var wire 4 " fifo_count [3:0] $end
$var wire 1 # empty $end
$var wire 8 $ data_out [7:0] $end
$var wire 1 % almost_full $end
$var wire 1 & almost_empty $end
$var parameter 32 ' ADDR_WIDTH $end
$var parameter 32 ( CLK_PERIOD $end
$var parameter 32 ) DATA_WIDTH $end
$var parameter 32 * FIFO_DEPTH $end
$var reg 1 + clk $end
$var reg 8 , data_in [7:0] $end
$var reg 1 - rd_en $end
$var reg 1 . rst_n $end
$var reg 1 / wr_en $end
$scope module dut $end
$var wire 1 + clk $end
$var wire 8 0 data_in [7:0] $end
$var wire 1 - rd_en $end
$var wire 1 . rst_n $end
$var wire 1 / wr_en $end
$var wire 1 ! full $end
$var wire 1 # empty $end
$var wire 1 % almost_full $end
$var wire 1 & almost_empty $end
$var parameter 32 1 ADDR_WIDTH $end
$var parameter 32 2 ALMOST_EMPTY_THRESHOLD $end
$var parameter 33 3 ALMOST_FULL_THRESHOLD $end
$var parameter 32 4 DATA_WIDTH $end
$var parameter 32 5 FIFO_DEPTH $end
$var reg 8 6 data_out [7:0] $end
$var reg 4 7 fifo_count [3:0] $end
$var reg 4 8 rd_ptr [3:0] $end
$var reg 4 9 wr_ptr [3:0] $end
$upscope $end
$upscope $end
$enddefinitions $end
$comment Show the parameter values. $end
$dumpall
b1000 5
b1000 4
b111 3
b1 2
b11 1
b1000 *
b1000 )
b1010 (
b11 '
$end
#0
$dumpvars
b0 9
b0 8
b0 7
b0 6
b0 0
0/
0.
0-
b0 ,
0+
1&
0%
b0 $
1#
b0 "
0!
$end
#5
1+
#10
0+
#15
1+
#20
0+
1.
#25
1+
#30
0+
#35
b1 9
0#
b1 "
b1 7
b1 ,
b1 0
1/
1+
#40
0+
#45
0&
b10 "
b10 7
b10 9
b10 ,
b10 0
1+
#50
0+
#55
b11 9
b11 "
b11 7
b11 ,
b11 0
1+
#60
0+
#65
b100 "
b100 7
b100 9
b100 ,
b100 0
1+
#70
0+
#75
b101 9
b101 "
b101 7
b101 ,
b101 0
1+
#80
0+
#85
b110 "
b110 7
b110 9
b110 ,
b110 0
1+
#90
0+
#95
b111 9
1%
b111 "
b111 7
b111 ,
b111 0
1+
#100
0+
#105
0/
1+
#110
0+
#115
b1000 9
1!
b1000 "
b1000 7
b1000 ,
b1000 0
1/
1+
#120
0+
#125
b11111111 ,
b11111111 0
1+
#130
0+
#135
0/
1+
#140
0+
#145
0!
b111 "
b111 7
b1 8
b1 $
b1 6
1-
1+
#150
0+
#155
0-
1+
#160
0+
#165
0%
b110 "
b110 7
b10 8
b10 $
b10 6
1-
1+
#170
0+
#175
0-
1+
#180
0+
#185
b101 "
b101 7
b11 8
b11 $
b11 6
1-
1+
#190
0+
#195
0-
1+
#200
0+
#205
b100 "
b100 7
b100 8
b100 $
b100 6
1-
1+
#210
0+
#215
0-
1+
#220
0+
#225
b11 "
b11 7
b101 8
b101 $
b101 6
1-
1+
#230
0+
#235
0-
1+
#240
0+
#245
b10 "
b10 7
b110 8
b110 $
b110 6
1-
1+
#250
0+
#255
0-
1+
#260
0+
#265
1&
b1 "
b1 7
b111 8
b111 $
b111 6
1-
1+
#270
0+
#275
0-
1+
#280
0+
#285
1#
b0 "
b0 7
b1000 8
b1000 $
b1000 6
1-
1+
#290
0+
#295
0-
1+
#300
0+
#305
b0 $
b0 6
1-
1+
#310
0+
#315
1+
#320
0+
#325
0-
1+
#330
0+
#335
b1001 9
0#
b1 "
b1 7
b10000 ,
b10000 0
1/
1+
#340
0+
#345
0/
1+
#350
0+
#355
b1010 9
b1001 8
b10000 $
b10000 6
b10001 ,
b10001 0
1-
1/
1+
#360
0+
#365
0-
0/
1+
#370
0+
#375
b1011 9
b1010 8
b10001 $
b10001 6
b10010 ,
b10010 0
1-
1/
1+
#380
0+
#385
0-
0/
1+
#390
0+
#395
b1100 9
b1011 8
b10010 $
b10010 6
b10011 ,
b10011 0
1-
1/
1+
#400
0+
#405
0-
0/
1+
